levmatch/__init__.py
levmatch/levmatch.py
levmatch-0.1.data/scripts/levmatch
levmatch-0.1.dist-info/METADATA
levmatch-0.1.dist-info/WHEEL
levmatch-0.1.dist-info/top_level.txt
levmatch-0.1.dist-info/RECORD
